send-email/__init__.py
send_email/__init__.py
send_email_python-0.0.1.dist-info/LICENSE
send_email_python-0.0.1.dist-info/METADATA
send_email_python-0.0.1.dist-info/WHEEL
send_email_python-0.0.1.dist-info/top_level.txt
send_email_python-0.0.1.dist-info/RECORD
