Metadata-Version: 2.1
Name: send-email-python
Version: 0.0.1
Summary: A package to simply send an email.
Home-page: https://github.com/pjaycorp/send-email-python
Author: Puranjay Prashanth
Author-email: puranjayprashanth@gmail.com
License: GNU
Platform: UNKNOWN
